ewccommons/__init__.py
ewccommons/__main__.py
ewccommons/__version__.py
ewccommons/carddeck.py
ewccommons/dice.py
ewccommons/dicerolls.py
ewccommons/errors.py
ewccommons/typing_extensions.py
ewccommons/sophie/__init__.py
ewccommons/sophie/errors.py
ewccommons/sophie/launcher.py
ewccommons/sophie/processors.py
ewccommons/sophie/usage.py
ewc_commons-0.0.1.11.dist-info/LICENSE
ewc_commons-0.0.1.11.dist-info/METADATA
ewc_commons-0.0.1.11.dist-info/WHEEL
ewc_commons-0.0.1.11.dist-info/entry_points.txt
ewc_commons-0.0.1.11.dist-info/top_level.txt
ewc_commons-0.0.1.11.dist-info/RECORD
