Metadata-Version: 2.1
Name: ewc-commons
Version: 0.0.1.11
Summary: Collection of common use stuff
Home-page: https://bitbucket.org/ewc-learning/ewc-commons/
Author: Evil Wizard Creations
Author-email: evil.wizard95@googlemail.com
License: UNKNOWN
Project-URL: Bug Reports, https://bitbucket.org/ewc-learning/ewc-commons/issues
Project-URL: Funding, https://donate.pypi.org
Project-URL: Say Thanks!, http://saythanks.io/to/example
Project-URL: Source, https://bitbucket.org/ewc-learning/ewc-commons/
Keywords: ewc,commons,library,sophie,cli,launcher,dice dice rolls,card deck
Platform: UNKNOWN
Classifier: Development Status :: 3 - Alpha
Classifier: Intended Audience :: Developers
Classifier: Topic :: Software Development :: Libraries
Classifier: License :: OSI Approved :: MIT License
Classifier: Programming Language :: Python :: 3
Classifier: Programming Language :: Python :: 3.7
Classifier: Programming Language :: Python :: 3.8
Classifier: Programming Language :: Python :: 3.9
Classifier: Programming Language :: Python :: 3 :: Only
Classifier: Operating System :: OS Independent
Requires-Python: >=3.7, <4
Provides-Extra: dev
Provides-Extra: test
Requires-Dist: coverage ; extra == 'test'
